cherrypy/__init__.py
cherrypy/__main__.py
cherrypy/_cpchecker.py
cherrypy/_cpcompat.py
cherrypy/_cpconfig.py
cherrypy/_cpdispatch.py
cherrypy/_cperror.py
cherrypy/_cplogging.py
cherrypy/_cpmodpy.py
cherrypy/_cpnative_server.py
cherrypy/_cpreqbody.py
cherrypy/_cprequest.py
cherrypy/_cpserver.py
cherrypy/_cptools.py
cherrypy/_cptree.py
cherrypy/_cpwsgi.py
cherrypy/_cpwsgi_server.py
cherrypy/_helper.py
cherrypy/_json.py
cherrypy/daemon.py
cherrypy/favicon.ico
cherrypy/lib/__init__.py
cherrypy/lib/auth_basic.py
cherrypy/lib/auth_digest.py
cherrypy/lib/caching.py
cherrypy/lib/covercp.py
cherrypy/lib/cpstats.py
cherrypy/lib/cptools.py
cherrypy/lib/encoding.py
cherrypy/lib/gctools.py
cherrypy/lib/headers.py
cherrypy/lib/httputil.py
cherrypy/lib/jsontools.py
cherrypy/lib/locking.py
cherrypy/lib/profiler.py
cherrypy/lib/reprconf.py
cherrypy/lib/sessions.py
cherrypy/lib/static.py
cherrypy/lib/xmlrpcutil.py
cherrypy/process/__init__.py
cherrypy/process/plugins.py
cherrypy/process/servers.py
cherrypy/process/win32.py
cherrypy/process/wspbus.py
cherrypy/scaffold/__init__.py
cherrypy/scaffold/apache-fcgi.conf
cherrypy/scaffold/example.conf
cherrypy/scaffold/site.conf
cherrypy/scaffold/static/made_with_cherrypy_small.png
cherrypy/test/__init__.py
cherrypy/test/_test_decorators.py
cherrypy/test/_test_states_demo.py
cherrypy/test/benchmark.py
cherrypy/test/checkerdemo.py
cherrypy/test/fastcgi.conf
cherrypy/test/fcgi.conf
cherrypy/test/helper.py
cherrypy/test/logtest.py
cherrypy/test/modfastcgi.py
cherrypy/test/modfcgid.py
cherrypy/test/modpy.py
cherrypy/test/modwsgi.py
cherrypy/test/sessiondemo.py
cherrypy/test/style.css
cherrypy/test/test.pem
cherrypy/test/test_auth_basic.py
cherrypy/test/test_auth_digest.py
cherrypy/test/test_bus.py
cherrypy/test/test_caching.py
cherrypy/test/test_config.py
cherrypy/test/test_config_server.py
cherrypy/test/test_conn.py
cherrypy/test/test_core.py
cherrypy/test/test_dynamicobjectmapping.py
cherrypy/test/test_encoding.py
cherrypy/test/test_etags.py
CherryPy-18.10.0.dist-info/LICENSE.md
CherryPy-18.10.0.dist-info/METADATA
CherryPy-18.10.0.dist-info/WHEEL
CherryPy-18.10.0.dist-info/entry_points.txt
CherryPy-18.10.0.dist-info/top_level.txt
CherryPy-18.10.0.dist-info/RECORD
