Metadata-Version: 2.1
Name: CherryPy
Version: 18.10.0
Summary: Object-Oriented HTTP framework
Home-page: https://www.cherrypy.dev
Author: CherryPy Team
Author-email: team@cherrypy.dev
Project-URL: CI: AppVeyor, https://ci.appveyor.com/project/cherrypy/cherrypy
Project-URL: CI: Travis, https://travis-ci.org/cherrypy/cherrypy
Project-URL: CI: Circle, https://circleci.com/gh/cherrypy/cherrypy
Project-URL: CI: GitHub, https://github.com/cherrypy/cherrypy/actions
Project-URL: Docs: RTD, https://docs.cherrypy.dev
Project-URL: GitHub: issues, https://github.com/cherrypy/cherrypy/issues
Project-URL: GitHub: repo, https://github.com/cherrypy/cherrypy
Project-URL: Tidelift: funding, https://tidelift.com/subscription/pkg/pypi-cherrypy?utm_source=pypi-cherrypy&utm_medium=referral&utm_campaign=pypi
Classifier: Development Status :: 5 - Production/Stable
Classifier: Environment :: Web Environment
Classifier: Intended Audience :: Developers
Classifier: License :: Freely Distributable
Classifier: Operating System :: OS Independent
Classifier: Framework :: CherryPy
Classifier: License :: OSI Approved :: BSD License
Classifier: Programming Language :: Python
Classifier: Programming Language :: Python :: 3
Classifier: Programming Language :: Python :: 3.6
Classifier: Programming Language :: Python :: 3.7
Classifier: Programming Language :: Python :: 3.8
Classifier: Programming Language :: Python :: 3.9
Classifier: Programming Language :: Python :: 3.10
Classifier: Programming Language :: Python :: 3.11
Classifier: Programming Language :: Python :: Implementation
Classifier: Programming Language :: Python :: Implementation :: CPython
Classifier: Programming Language :: Python :: Implementation :: Jython
Classifier: Programming Language :: Python :: Implementation :: PyPy
Classifier: Topic :: Internet :: WWW/HTTP
Classifier: Topic :: Internet :: WWW/HTTP :: Dynamic Content
Classifier: Topic :: Internet :: WWW/HTTP :: HTTP Servers
Classifier: Topic :: Internet :: WWW/HTTP :: WSGI
Classifier: Topic :: Internet :: WWW/HTTP :: WSGI :: Application
Classifier: Topic :: Internet :: WWW/HTTP :: WSGI :: Server
Classifier: Topic :: Software Development :: Libraries :: Application Frameworks
Requires-Python: >=3.6
License-File: LICENSE.md
Requires-Dist: cheroot>=8.2.1
Requires-Dist: portend>=2.1.1
Requires-Dist: more_itertools
Requires-Dist: zc.lockfile
Requires-Dist: jaraco.collections
Requires-Dist: importlib-metadata; python_version <= "3.7"
Provides-Extra: docs
Requires-Dist: sphinx; extra == "docs"
Requires-Dist: docutils; extra == "docs"
Requires-Dist: alabaster; extra == "docs"
Requires-Dist: sphinxcontrib-apidoc>=0.3.0; extra == "docs"
Requires-Dist: rst.linker>=1.11; extra == "docs"
Requires-Dist: jaraco.packaging>=3.2; extra == "docs"
Provides-Extra: json
Requires-Dist: simplejson; extra == "json"
Provides-Extra: routes-dispatcher
Requires-Dist: routes>=2.3.1; extra == "routes-dispatcher"
Provides-Extra: ssl
Requires-Dist: pyOpenSSL; extra == "ssl"
Provides-Extra: testing
Requires-Dist: objgraph; extra == "testing"
Requires-Dist: pytest>=5.3.5; extra == "testing"
Requires-Dist: pytest-cov; extra == "testing"
Requires-Dist: pytest-forked; extra == "testing"
Requires-Dist: pytest-sugar; extra == "testing"
Requires-Dist: path.py; extra == "testing"
Requires-Dist: requests_toolbelt; extra == "testing"
Requires-Dist: pytest-services>=2; extra == "testing"
Requires-Dist: setuptools; extra == "testing"
Provides-Extra: memcached-session
Requires-Dist: python-memcached>=1.58; extra == "memcached-session"
Provides-Extra: xcgi
Requires-Dist: flup; extra == "xcgi"
Requires-Dist: pywin32>=227; sys_platform == "win32" and implementation_name == "cpython" and python_version < "3.10"
